monitoring/__init__.py
monitoring/monitoring.py
monitoring/post_payloads.py
ops_py_monitoring-6.0.3.dist-info/licenses/LICENSE
ops_py_monitoring-6.0.3.dist-info/METADATA
ops_py_monitoring-6.0.3.dist-info/WHEEL
ops_py_monitoring-6.0.3.dist-info/top_level.txt
ops_py_monitoring-6.0.3.dist-info/RECORD
