Metadata-Version: 2.4
Name: ops-py-monitoring
Version: 6.0.3
Summary: Post Key Vault Secrets report to webhook
License: MIT License
License-File: LICENSE
Requires-Dist: backports.tarfile==1.2.0
Requires-Dist: beautifulsoup4==4.12.3
Requires-Dist: build==1.2.2.post1
Requires-Dist: certifi==2024.8.30
Requires-Dist: charset-normalizer==3.4.0
Requires-Dist: docutils==0.21.2
Requires-Dist: idna==3.10
Requires-Dist: importlib_metadata==8.5.0
Requires-Dist: jaraco.classes==3.4.0
Requires-Dist: jaraco.context==6.0.1
Requires-Dist: jaraco.functools==4.1.0
Requires-Dist: keyring==25.5.0
Requires-Dist: markdown-it-py==3.0.0
Requires-Dist: mdurl==0.1.2
Requires-Dist: more-itertools==10.5.0
Requires-Dist: nh3==0.2.18
Requires-Dist: ops-py-azure-key-vault-report==8.0.2
Requires-Dist: ops-py-cert-report==5.0.3
Requires-Dist: ops-py-generate-pyproject==2.2.3
Requires-Dist: ops-py-message-handler==1.0.7
Requires-Dist: ops-py-reports==0.6.0
Requires-Dist: packaging==24.2
Requires-Dist: pip==24.3.1
Requires-Dist: pkginfo==1.10.0
Requires-Dist: Pygments==2.18.0
Requires-Dist: pyproject_hooks==1.2.0
Requires-Dist: readme_renderer==44.0
Requires-Dist: requests==2.32.3
Requires-Dist: requests-toolbelt==1.0.0
Requires-Dist: rfc3986==2.0.0
Requires-Dist: rich==13.9.4
Requires-Dist: setuptools==75.5.0
Requires-Dist: soupsieve==2.6
Requires-Dist: twine==5.1.1
Requires-Dist: urllib3==2.2.3
Requires-Dist: wheel==0.45.0
Requires-Dist: zipp==3.21.0
Dynamic: license-file
